csv_query/__init__.py
csv_query/core.py
csv_query/main.py
csvquerylite-0.1.5.dist-info/LICENSE
csvquerylite-0.1.5.dist-info/METADATA
csvquerylite-0.1.5.dist-info/WHEEL
csvquerylite-0.1.5.dist-info/entry_points.txt
csvquerylite-0.1.5.dist-info/top_level.txt
csvquerylite-0.1.5.dist-info/RECORD
