Metadata-Version: 2.1
Name: csvquerylite
Version: 0.1.5
Summary: Run SQL-like queries on CSV files using a simple Python library or CLI.
Home-page: https://github.com/jah-117/csvquerylite
Author: Jahfar Muhammed
Author-email: jahfarbinmuhammed117@gmail.com
License: UNKNOWN
Platform: UNKNOWN
Classifier: Programming Language :: Python :: 3
Classifier: License :: OSI Approved :: MIT License
Classifier: Operating System :: OS Independent
Requires-Python: >=3.6
License-File: LICENSE
Requires-Dist: pandas
